{
    "result1": {
        "date": "2023-07-03 22:04:38.755641",
        "result": 51
    },
    "result2": {
        "date": "2023-07-03 22:05:16.000298",
        "result": 39
    },
    "result3": {
        "date": "2023-07-03 22:08:50.623444",
        "result": 40
    },
    "result4": {
        "date": "2023-07-03 22:09:56.839620",
        "result": 2
    },
    "result5": {
        "date": "2023-07-03 22:30:02.738301",
        "result": 84,
        "wave": 4
    },
    "result6": {
        "date": "2023-07-04 15:55:53.884488",
        "result": 46,
        "wave": 3
    },
    "result7": {
        "date": "2023-07-04 15:58:06.553444",
        "result": 43,
        "wave": 3
    },
    "result8": {
        "date": "2023-07-04 16:01:53.587795",
        "result": 64,
        "wave": 3
    },
    "result9": {
        "date": "2023-07-04 16:23:36.591322",
        "result": 37,
        "wave": 2
    },
    "result10": {
        "date": "2023-07-06 18:33:23.396712",
        "result": 31,
        "wave": 2
    },
    "result11": {
        "date": "2023-07-06 18:52:16.564873",
        "result": 26,
        "wave": 2
    },
    "result12": {
        "date": "2023-07-06 18:57:30.065617",
        "result": 55,
        "wave": 4
    },
    "result13": {
        "date": "2023-07-06 18:58:11.623473",
        "result": 35,
        "wave": 3
    },
    "result14": {
        "date": "2023-07-06 18:59:52.348152",
        "result": 70,
        "wave": 4
    },
    "result15": {
        "date": "2023-07-06 19:52:29.465360",
        "result": 58,
        "wave": 4
    },
    "result16": {
        "date": "2023-07-06 19:54:01.070822",
        "result": 59,
        "wave": 4
    },
    "result17": {
        "date": "2023-07-06 19:55:38.840714",
        "result": 64,
        "wave": 4
    },
    "result18": {
        "date": "2023-07-06 20:08:17.660835",
        "result": 159,
        "wave": 6
    },
    "result19": {
        "date": "2023-07-06 20:10:04.384983",
        "result": 119,
        "wave": 5
    }
}